{"@context":"http://iiif.io/api/presentation/2/context.json","@id":"https://readux.ecdsdev.org/iiif/v2/2qfw5j4k/list/2qfw5j4k_00000279.jpg","@type":"sc:AnnotationList","resources":[{"@context":"http://iiif.io/api/presentation/2/context.json","@id":"ce57f631-f383-4e84-9db3-ce50d691a2e1","@type":"oa:Annotation","motivation":"sc:painting","annotatedBy":{"name":"OCR"},"resource":{"@type":"cnt:ContentAsText","format":"text/html","chars":"<span id='ce57f631-f383-4e84-9db3-ce50d691a2e1' class='anno-ce57f631-f383-4e84-9db3-ce50d691a2e1' data-letter-spacing='-0.037162162162162164'>Sran</span>","language":"en"},"on":{"full":"https://readux.ecdsdev.org/iiif/v2/2qfw5j4k/canvas/2qfw5j4k_00000279.jpg","@type":"oa:SpecificResource","within":{"@id":"https://readux.ecdsdev.org/iiif/v2/2qfw5j4k/manifest","@type":"sc:Manifest"},"selector":{"@type":"oa:FragmentSelector","value":"xywh=2,418,37,34","item":{"@type":"oa:FragmentSelector"}}},"stylesheet":{"type":"CssStylesheet","value":".anno-ce57f631-f383-4e84-9db3-ce50d691a2e1: { height: 34px; width: 37px; font-size: 21.25px; letter-spacing: -1.375px;}"}},{"@context":"http://iiif.io/api/presentation/2/context.json","@id":"400252b8-66e6-40dd-a88b-e25c79c4f40a","@type":"oa:Annotation","motivation":"sc:painting","annotatedBy":{"name":"OCR"},"resource":{"@type":"cnt:ContentAsText","format":"text/html","chars":"<span id='400252b8-66e6-40dd-a88b-e25c79c4f40a' class='anno-400252b8-66e6-40dd-a88b-e25c79c4f40a' data-letter-spacing='-0.08191287878787878'>terali</span>","language":"en"},"on":{"full":"https://readux.ecdsdev.org/iiif/v2/2qfw5j4k/canvas/2qfw5j4k_00000279.jpg","@type":"oa:SpecificResource","within":{"@id":"https://readux.ecdsdev.org/iiif/v2/2qfw5j4k/manifest","@type":"sc:Manifest"},"selector":{"@type":"oa:FragmentSelector","value":"xywh=2,474,44,35","item":{"@type":"oa:FragmentSelector"}}},"stylesheet":{"type":"CssStylesheet","value":".anno-400252b8-66e6-40dd-a88b-e25c79c4f40a: { height: 35px; width: 44px; font-size: 21.875px; letter-spacing: -3.6041666666666665px;}"}},{"@context":"http://iiif.io/api/presentation/2/context.json","@id":"d99ed7ba-2eb4-4de9-9403-ed87168c686f","@type":"oa:Annotation","motivation":"sc:painting","annotatedBy":{"name":"OCR"},"resource":{"@type":"cnt:ContentAsText","format":"text/html","chars":"<span id='d99ed7ba-2eb4-4de9-9403-ed87168c686f' class='anno-d99ed7ba-2eb4-4de9-9403-ed87168c686f' data-letter-spacing='-0.15327380952380953'>Urbino</span>","language":"en"},"on":{"full":"https://readux.ecdsdev.org/iiif/v2/2qfw5j4k/canvas/2qfw5j4k_00000279.jpg","@type":"oa:SpecificResource","within":{"@id":"https://readux.ecdsdev.org/iiif/v2/2qfw5j4k/manifest","@type":"sc:Manifest"},"selector":{"@type":"oa:FragmentSelector","value":"xywh=5,792,42,43","item":{"@type":"oa:FragmentSelector"}}},"stylesheet":{"type":"CssStylesheet","value":".anno-d99ed7ba-2eb4-4de9-9403-ed87168c686f: { height: 43px; width: 42px; font-size: 26.875px; letter-spacing: -6.4375px;}"}},{"@context":"http://iiif.io/api/presentation/2/context.json","@id":"02715ff0-a12f-42c9-9dba-cdaaa38f5a60","@type":"oa:Annotation","motivation":"sc:painting","annotatedBy":{"name":"OCR"},"resource":{"@type":"cnt:ContentAsText","format":"text/html","chars":"<span id='02715ff0-a12f-42c9-9dba-cdaaa38f5a60' class='anno-02715ff0-a12f-42c9-9dba-cdaaa38f5a60' data-letter-spacing='-0.08658854166666667'>200</span>","language":"en"},"on":{"full":"https://readux.ecdsdev.org/iiif/v2/2qfw5j4k/canvas/2qfw5j4k_00000279.jpg","@type":"oa:SpecificResource","within":{"@id":"https://readux.ecdsdev.org/iiif/v2/2qfw5j4k/manifest","@type":"sc:Manifest"},"selector":{"@type":"oa:FragmentSelector","value":"xywh=-5,956,32,43","item":{"@type":"oa:FragmentSelector"}}},"stylesheet":{"type":"CssStylesheet","value":".anno-02715ff0-a12f-42c9-9dba-cdaaa38f5a60: { height: 43px; width: 32px; font-size: 26.875px; letter-spacing: -2.7708333333333335px;}"}},{"@context":"http://iiif.io/api/presentation/2/context.json","@id":"9de2f67b-24a4-41f3-8f8c-cfc7b5b59dc5","@type":"oa:Annotation","motivation":"sc:painting","annotatedBy":{"name":"OCR"},"resource":{"@type":"cnt:ContentAsText","format":"text/html","chars":"<span id='9de2f67b-24a4-41f3-8f8c-cfc7b5b59dc5' class='anno-9de2f67b-24a4-41f3-8f8c-cfc7b5b59dc5' data-letter-spacing='-0.028846153846153848'>M2</span>","language":"en"},"on":{"full":"https://readux.ecdsdev.org/iiif/v2/2qfw5j4k/canvas/2qfw5j4k_00000279.jpg","@type":"oa:SpecificResource","within":{"@id":"https://readux.ecdsdev.org/iiif/v2/2qfw5j4k/manifest","@type":"sc:Manifest"},"selector":{"@type":"oa:FragmentSelector","value":"xywh=30,954,26,44","item":{"@type":"oa:FragmentSelector"}}},"stylesheet":{"type":"CssStylesheet","value":".anno-9de2f67b-24a4-41f3-8f8c-cfc7b5b59dc5: { height: 44px; width: 26px; font-size: 27.5px; letter-spacing: -0.75px;}"}},{"@context":"http://iiif.io/api/presentation/2/context.json","@id":"0fcdecfc-da23-4c5c-8d4a-0b853414c61e","@type":"oa:Annotation","motivation":"sc:painting","annotatedBy":{"name":"OCR"},"resource":{"@type":"cnt:ContentAsText","format":"text/html","chars":"<span id='0fcdecfc-da23-4c5c-8d4a-0b853414c61e' class='anno-0fcdecfc-da23-4c5c-8d4a-0b853414c61e' data-letter-spacing='-0.1111111111111111'>pela</span>","language":"en"},"on":{"full":"https://readux.ecdsdev.org/iiif/v2/2qfw5j4k/canvas/2qfw5j4k_00000279.jpg","@type":"oa:SpecificResource","within":{"@id":"https://readux.ecdsdev.org/iiif/v2/2qfw5j4k/manifest","@type":"sc:Manifest"},"selector":{"@type":"oa:FragmentSelector","value":"xywh=-2,1012,45,52","item":{"@type":"oa:FragmentSelector"}}},"stylesheet":{"type":"CssStylesheet","value":".anno-0fcdecfc-da23-4c5c-8d4a-0b853414c61e: { height: 52px; width: 45px; font-size: 32.5px; letter-spacing: -5.0px;}"}},{"@context":"http://iiif.io/api/presentation/2/context.json","@id":"5f7242c2-b586-4576-82d0-30cbb8eca253","@type":"oa:Annotation","motivation":"sc:painting","annotatedBy":{"name":"OCR"},"resource":{"@type":"cnt:ContentAsText","format":"text/html","chars":"<span id='5f7242c2-b586-4576-82d0-30cbb8eca253' class='anno-5f7242c2-b586-4576-82d0-30cbb8eca253' data-letter-spacing='-0.90625'>se</span>","language":"en"},"on":{"full":"https://readux.ecdsdev.org/iiif/v2/2qfw5j4k/canvas/2qfw5j4k_00000279.jpg","@type":"oa:SpecificResource","within":{"@id":"https://readux.ecdsdev.org/iiif/v2/2qfw5j4k/manifest","@type":"sc:Manifest"},"selector":{"@type":"oa:FragmentSelector","value":"xywh=47,1010,12,54","item":{"@type":"oa:FragmentSelector"}}},"stylesheet":{"type":"CssStylesheet","value":".anno-5f7242c2-b586-4576-82d0-30cbb8eca253: { height: 54px; width: 12px; font-size: 33.75px; letter-spacing: -10.875px;}"}},{"@context":"http://iiif.io/api/presentation/2/context.json","@id":"adba431a-b1cf-4b40-9d95-215e0dd52240","@type":"oa:Annotation","motivation":"sc:painting","annotatedBy":{"name":"OCR"},"resource":{"@type":"cnt:ContentAsText","format":"text/html","chars":"<span id='adba431a-b1cf-4b40-9d95-215e0dd52240' class='anno-adba431a-b1cf-4b40-9d95-215e0dd52240' data-letter-spacing='-0.043821839080459765'>nam</span>","language":"en"},"on":{"full":"https://readux.ecdsdev.org/iiif/v2/2qfw5j4k/canvas/2qfw5j4k_00000279.jpg","@type":"oa:SpecificResource","within":{"@id":"https://readux.ecdsdev.org/iiif/v2/2qfw5j4k/manifest","@type":"sc:Manifest"},"selector":{"@type":"oa:FragmentSelector","value":"xywh=-3,1074,29,35","item":{"@type":"oa:FragmentSelector"}}},"stylesheet":{"type":"CssStylesheet","value":".anno-adba431a-b1cf-4b40-9d95-215e0dd52240: { height: 35px; width: 29px; font-size: 21.875px; letter-spacing: -1.2708333333333333px;}"}},{"@context":"http://iiif.io/api/presentation/2/context.json","@id":"428a9de2-2028-43da-94fc-04f1a7cf3050","@type":"oa:Annotation","motivation":"sc:painting","annotatedBy":{"name":"OCR"},"resource":{"@type":"cnt:ContentAsText","format":"text/html","chars":"<span id='428a9de2-2028-43da-94fc-04f1a7cf3050' class='anno-428a9de2-2028-43da-94fc-04f1a7cf3050' data-letter-spacing='-0.2152777777777778'>:</span>","language":"en"},"on":{"full":"https://readux.ecdsdev.org/iiif/v2/2qfw5j4k/canvas/2qfw5j4k_00000279.jpg","@type":"oa:SpecificResource","within":{"@id":"https://readux.ecdsdev.org/iiif/v2/2qfw5j4k/manifest","@type":"sc:Manifest"},"selector":{"@type":"oa:FragmentSelector","value":"xywh=30,1074,9,35","item":{"@type":"oa:FragmentSelector"}}},"stylesheet":{"type":"CssStylesheet","value":".anno-428a9de2-2028-43da-94fc-04f1a7cf3050: { height: 35px; width: 9px; font-size: 21.875px; letter-spacing: -1.9375px;}"}},{"@context":"http://iiif.io/api/presentation/2/context.json","@id":"66e8c54b-f8fd-453c-b931-1c1ce1a3f7e7","@type":"oa:Annotation","motivation":"sc:painting","annotatedBy":{"name":"OCR"},"resource":{"@type":"cnt:ContentAsText","format":"text/html","chars":"<span id='66e8c54b-f8fd-453c-b931-1c1ce1a3f7e7' class='anno-66e8c54b-f8fd-453c-b931-1c1ce1a3f7e7' data-letter-spacing='-0.05921052631578947'>CE</span>","language":"en"},"on":{"full":"https://readux.ecdsdev.org/iiif/v2/2qfw5j4k/canvas/2qfw5j4k_00000279.jpg","@type":"oa:SpecificResource","within":{"@id":"https://readux.ecdsdev.org/iiif/v2/2qfw5j4k/manifest","@type":"sc:Manifest"},"selector":{"@type":"oa:FragmentSelector","value":"xywh=39,1074,19,34","item":{"@type":"oa:FragmentSelector"}}},"stylesheet":{"type":"CssStylesheet","value":".anno-66e8c54b-f8fd-453c-b931-1c1ce1a3f7e7: { height: 34px; width: 19px; font-size: 21.25px; letter-spacing: -1.125px;}"}},{"@context":"http://iiif.io/api/presentation/2/context.json","@id":"ace39f5f-082e-4aed-b8f2-1ab827837256","@type":"oa:Annotation","motivation":"sc:painting","annotatedBy":{"name":"OCR"},"resource":{"@type":"cnt:ContentAsText","format":"text/html","chars":"<span id='ace39f5f-082e-4aed-b8f2-1ab827837256' class='anno-ace39f5f-082e-4aed-b8f2-1ab827837256' data-letter-spacing='0.43080357142857145'>I</span>","language":"en"},"on":{"full":"https://readux.ecdsdev.org/iiif/v2/2qfw5j4k/canvas/2qfw5j4k_00000279.jpg","@type":"oa:SpecificResource","within":{"@id":"https://readux.ecdsdev.org/iiif/v2/2qfw5j4k/manifest","@type":"sc:Manifest"},"selector":{"@type":"oa:FragmentSelector","value":"xywh=-12,1676,28,51","item":{"@type":"oa:FragmentSelector"}}},"stylesheet":{"type":"CssStylesheet","value":".anno-ace39f5f-082e-4aed-b8f2-1ab827837256: { height: 51px; width: 28px; font-size: 31.875px; letter-spacing: 12.0625px;}"}},{"@context":"http://iiif.io/api/presentation/2/context.json","@id":"f965eb3f-ee60-4ad5-a0fa-8422716f12c4","@type":"oa:Annotation","motivation":"sc:painting","annotatedBy":{"name":"OCR"},"resource":{"@type":"cnt:ContentAsText","format":"text/html","chars":"<span id='f965eb3f-ee60-4ad5-a0fa-8422716f12c4' class='anno-f965eb3f-ee60-4ad5-a0fa-8422716f12c4' data-letter-spacing='-0.11282467532467533'>allegro</span>","language":"en"},"on":{"full":"https://readux.ecdsdev.org/iiif/v2/2qfw5j4k/canvas/2qfw5j4k_00000279.jpg","@type":"oa:SpecificResource","within":{"@id":"https://readux.ecdsdev.org/iiif/v2/2qfw5j4k/manifest","@type":"sc:Manifest"},"selector":{"@type":"oa:FragmentSelector","value":"xywh=10,1671,55,45","item":{"@type":"oa:FragmentSelector"}}},"stylesheet":{"type":"CssStylesheet","value":".anno-f965eb3f-ee60-4ad5-a0fa-8422716f12c4: { height: 45px; width: 55px; font-size: 28.125px; letter-spacing: -6.205357142857143px;}"}},{"@context":"http://iiif.io/api/presentation/2/context.json","@id":"ab6e01d3-ccbf-4714-bb32-343adb22c17b","@type":"oa:Annotation","motivation":"sc:painting","annotatedBy":{"name":"OCR"},"resource":{"@type":"cnt:ContentAsText","format":"text/html","chars":"<span id='ab6e01d3-ccbf-4714-bb32-343adb22c17b' class='anno-ab6e01d3-ccbf-4714-bb32-343adb22c17b' data-letter-spacing='-0.09069767441860464'>retti</span>","language":"en"},"on":{"full":"https://readux.ecdsdev.org/iiif/v2/2qfw5j4k/canvas/2qfw5j4k_00000279.jpg","@type":"oa:SpecificResource","within":{"@id":"https://readux.ecdsdev.org/iiif/v2/2qfw5j4k/manifest","@type":"sc:Manifest"},"selector":{"@type":"oa:FragmentSelector","value":"xywh=-5,1724,43,40","item":{"@type":"oa:FragmentSelector"}}},"stylesheet":{"type":"CssStylesheet","value":".anno-ab6e01d3-ccbf-4714-bb32-343adb22c17b: { height: 40px; width: 43px; font-size: 25.0px; letter-spacing: -3.9px;}"}},{"@context":"http://iiif.io/api/presentation/2/context.json","@id":"f8b67056-3562-4af7-8539-76476d687e84","@type":"oa:Annotation","motivation":"sc:painting","annotatedBy":{"name":"OCR"},"resource":{"@type":"cnt:ContentAsText","format":"text/html","chars":"<span id='f8b67056-3562-4af7-8539-76476d687e84' class='anno-f8b67056-3562-4af7-8539-76476d687e84' data-letter-spacing='-0.30654761904761907'>com</span>","language":"en"},"on":{"full":"https://readux.ecdsdev.org/iiif/v2/2qfw5j4k/canvas/2qfw5j4k_00000279.jpg","@type":"oa:SpecificResource","within":{"@id":"https://readux.ecdsdev.org/iiif/v2/2qfw5j4k/manifest","@type":"sc:Manifest"},"selector":{"@type":"oa:FragmentSelector","value":"xywh=38,1720,21,43","item":{"@type":"oa:FragmentSelector"}}},"stylesheet":{"type":"CssStylesheet","value":".anno-f8b67056-3562-4af7-8539-76476d687e84: { height: 43px; width: 21px; font-size: 26.875px; letter-spacing: -6.4375px;}"}},{"@context":"http://iiif.io/api/presentation/2/context.json","@id":"86338a0e-d5e3-4414-8c11-db6c4161d42a","@type":"oa:Annotation","motivation":"sc:painting","annotatedBy":{"name":"OCR"},"resource":{"@type":"cnt:ContentAsText","format":"text/html","chars":"<span id='86338a0e-d5e3-4414-8c11-db6c4161d42a' class='anno-86338a0e-d5e3-4414-8c11-db6c4161d42a' data-letter-spacing='0.019230769230769232'>il</span>","language":"en"},"on":{"full":"https://readux.ecdsdev.org/iiif/v2/2qfw5j4k/canvas/2qfw5j4k_00000279.jpg","@type":"oa:SpecificResource","within":{"@id":"https://readux.ecdsdev.org/iiif/v2/2qfw5j4k/manifest","@type":"sc:Manifest"},"selector":{"@type":"oa:FragmentSelector","value":"xywh=5,1778,26,40","item":{"@type":"oa:FragmentSelector"}}},"stylesheet":{"type":"CssStylesheet","value":".anno-86338a0e-d5e3-4414-8c11-db6c4161d42a: { height: 40px; width: 26px; font-size: 25.0px; letter-spacing: 0.5px;}"}},{"@context":"http://iiif.io/api/presentation/2/context.json","@id":"6efe4e83-42c8-4a05-8073-5aa589febd86","@type":"oa:Annotation","motivation":"sc:painting","annotatedBy":{"name":"OCR"},"resource":{"@type":"cnt:ContentAsText","format":"text/html","chars":"<span id='6efe4e83-42c8-4a05-8073-5aa589febd86' class='anno-6efe4e83-42c8-4a05-8073-5aa589febd86' data-letter-spacing='-0.09821428571428571'>colo</span>","language":"en"},"on":{"full":"https://readux.ecdsdev.org/iiif/v2/2qfw5j4k/canvas/2qfw5j4k_00000279.jpg","@type":"oa:SpecificResource","within":{"@id":"https://readux.ecdsdev.org/iiif/v2/2qfw5j4k/manifest","@type":"sc:Manifest"},"selector":{"@type":"oa:FragmentSelector","value":"xywh=29,1773,35,39","item":{"@type":"oa:FragmentSelector"}}},"stylesheet":{"type":"CssStylesheet","value":".anno-6efe4e83-42c8-4a05-8073-5aa589febd86: { height: 39px; width: 35px; font-size: 24.375px; letter-spacing: -3.4375px;}"}},{"@context":"http://iiif.io/api/presentation/2/context.json","@id":"682f529d-0d7a-48bb-a6b4-adf589c65da7","@type":"oa:Annotation","motivation":"sc:painting","annotatedBy":{"name":"OCR"},"resource":{"@type":"cnt:ContentAsText","format":"text/html","chars":"<span id='682f529d-0d7a-48bb-a6b4-adf589c65da7' class='anno-682f529d-0d7a-48bb-a6b4-adf589c65da7' data-letter-spacing='0.0024509803921568627'>ato</span>","language":"en"},"on":{"full":"https://readux.ecdsdev.org/iiif/v2/2qfw5j4k/canvas/2qfw5j4k_00000279.jpg","@type":"oa:SpecificResource","within":{"@id":"https://readux.ecdsdev.org/iiif/v2/2qfw5j4k/manifest","@type":"sc:Manifest"},"selector":{"@type":"oa:FragmentSelector","value":"xywh=0,1999,34,36","item":{"@type":"oa:FragmentSelector"}}},"stylesheet":{"type":"CssStylesheet","value":".anno-682f529d-0d7a-48bb-a6b4-adf589c65da7: { height: 36px; width: 34px; font-size: 22.5px; letter-spacing: 0.08333333333333333px;}"}},{"@context":"http://iiif.io/api/presentation/2/context.json","@id":"d69a1639-e135-4eb4-80fe-b89e7ef1aaa6","@type":"oa:Annotation","motivation":"sc:painting","annotatedBy":{"name":"OCR"},"resource":{"@type":"cnt:ContentAsText","format":"text/html","chars":"<span id='d69a1639-e135-4eb4-80fe-b89e7ef1aaa6' class='anno-d69a1639-e135-4eb4-80fe-b89e7ef1aaa6' data-letter-spacing='0.08051470588235293'>2.COM</span>","language":"en"},"on":{"full":"https://readux.ecdsdev.org/iiif/v2/2qfw5j4k/canvas/2qfw5j4k_00000279.jpg","@type":"oa:SpecificResource","within":{"@id":"https://readux.ecdsdev.org/iiif/v2/2qfw5j4k/manifest","@type":"sc:Manifest"},"selector":{"@type":"oa:FragmentSelector","value":"xywh=-10,2060,68,26","item":{"@type":"oa:FragmentSelector"}}},"stylesheet":{"type":"CssStylesheet","value":".anno-d69a1639-e135-4eb4-80fe-b89e7ef1aaa6: { height: 26px; width: 68px; font-size: 16.25px; letter-spacing: 5.475px;}"}},{"@context":"http://iiif.io/api/presentation/2/context.json","@id":"0675ee49-d754-4e61-be00-ce8fec63daa3","@type":"oa:Annotation","motivation":"sc:painting","annotatedBy":{"name":"OCR"},"resource":{"@type":"cnt:ContentAsText","format":"text/html","chars":"<span id='0675ee49-d754-4e61-be00-ce8fec63daa3' class='anno-0675ee49-d754-4e61-be00-ce8fec63daa3' data-letter-spacing='0.010638297872340425'>nato</span>","language":"en"},"on":{"full":"https://readux.ecdsdev.org/iiif/v2/2qfw5j4k/canvas/2qfw5j4k_00000279.jpg","@type":"oa:SpecificResource","within":{"@id":"https://readux.ecdsdev.org/iiif/v2/2qfw5j4k/manifest","@type":"sc:Manifest"},"selector":{"@type":"oa:FragmentSelector","value":"xywh=-7,2103,47,36","item":{"@type":"oa:FragmentSelector"}}},"stylesheet":{"type":"CssStylesheet","value":".anno-0675ee49-d754-4e61-be00-ce8fec63daa3: { height: 36px; width: 47px; font-size: 22.5px; letter-spacing: 0.5px;}"}},{"@context":"http://iiif.io/api/presentation/2/context.json","@id":"22afa70c-a973-4841-b18d-cc2dc5c4585d","@type":"oa:Annotation","motivation":"sc:painting","annotatedBy":{"name":"OCR"},"resource":{"@type":"cnt:ContentAsText","format":"text/html","chars":"<span id='22afa70c-a973-4841-b18d-cc2dc5c4585d' class='anno-22afa70c-a973-4841-b18d-cc2dc5c4585d' data-letter-spacing='-0.21691176470588236'>di</span>","language":"en"},"on":{"full":"https://readux.ecdsdev.org/iiif/v2/2qfw5j4k/canvas/2qfw5j4k_00000279.jpg","@type":"oa:SpecificResource","within":{"@id":"https://readux.ecdsdev.org/iiif/v2/2qfw5j4k/manifest","@type":"sc:Manifest"},"selector":{"@type":"oa:FragmentSelector","value":"xywh=41,2097,17,39","item":{"@type":"oa:FragmentSelector"}}},"stylesheet":{"type":"CssStylesheet","value":".anno-22afa70c-a973-4841-b18d-cc2dc5c4585d: { height: 39px; width: 17px; font-size: 24.375px; letter-spacing: -3.6875px;}"}},{"@context":"http://iiif.io/api/presentation/2/context.json","@id":"9ae95777-691b-46eb-82cb-1e98e2bfb1a8","@type":"oa:Annotation","motivation":"sc:painting","annotatedBy":{"name":"OCR"},"resource":{"@type":"cnt:ContentAsText","format":"text/html","chars":"<span id='9ae95777-691b-46eb-82cb-1e98e2bfb1a8' class='anno-9ae95777-691b-46eb-82cb-1e98e2bfb1a8' data-letter-spacing='0.06979166666666667'>otara</span>","language":"en"},"on":{"full":"https://readux.ecdsdev.org/iiif/v2/2qfw5j4k/canvas/2qfw5j4k_00000279.jpg","@type":"oa:SpecificResource","within":{"@id":"https://readux.ecdsdev.org/iiif/v2/2qfw5j4k/manifest","@type":"sc:Manifest"},"selector":{"@type":"oa:FragmentSelector","value":"xywh=-3,2215,60,25","item":{"@type":"oa:FragmentSelector"}}},"stylesheet":{"type":"CssStylesheet","value":".anno-9ae95777-691b-46eb-82cb-1e98e2bfb1a8: { height: 25px; width: 60px; font-size: 15.625px; letter-spacing: 4.1875px;}"}},{"@context":"http://iiif.io/api/presentation/2/context.json","@id":"ce57f631-f383-4e84-9db3-ce50d691a2e1","@type":"oa:Annotation","motivation":"sc:painting","annotatedBy":{"name":"OCR"},"resource":{"@type":"cnt:ContentAsText","format":"text/html","chars":"<span id='ce57f631-f383-4e84-9db3-ce50d691a2e1' class='anno-ce57f631-f383-4e84-9db3-ce50d691a2e1' data-letter-spacing='-0.037162162162162164'>Sran</span>","language":"en"},"on":{"full":"https://readux.ecdsdev.org/iiif/v2/2qfw5j4k/canvas/2qfw5j4k_00000279.jpg","@type":"oa:SpecificResource","within":{"@id":"https://readux.ecdsdev.org/iiif/v2/2qfw5j4k/manifest","@type":"sc:Manifest"},"selector":{"@type":"oa:FragmentSelector","value":"xywh=2,418,37,34","item":{"@type":"oa:FragmentSelector"}}},"stylesheet":{"type":"CssStylesheet","value":".anno-ce57f631-f383-4e84-9db3-ce50d691a2e1: { height: 34px; width: 37px; font-size: 21.25px; letter-spacing: -1.375px;}"}},{"@context":"http://iiif.io/api/presentation/2/context.json","@id":"400252b8-66e6-40dd-a88b-e25c79c4f40a","@type":"oa:Annotation","motivation":"sc:painting","annotatedBy":{"name":"OCR"},"resource":{"@type":"cnt:ContentAsText","format":"text/html","chars":"<span id='400252b8-66e6-40dd-a88b-e25c79c4f40a' class='anno-400252b8-66e6-40dd-a88b-e25c79c4f40a' data-letter-spacing='-0.08191287878787878'>terali</span>","language":"en"},"on":{"full":"https://readux.ecdsdev.org/iiif/v2/2qfw5j4k/canvas/2qfw5j4k_00000279.jpg","@type":"oa:SpecificResource","within":{"@id":"https://readux.ecdsdev.org/iiif/v2/2qfw5j4k/manifest","@type":"sc:Manifest"},"selector":{"@type":"oa:FragmentSelector","value":"xywh=2,474,44,35","item":{"@type":"oa:FragmentSelector"}}},"stylesheet":{"type":"CssStylesheet","value":".anno-400252b8-66e6-40dd-a88b-e25c79c4f40a: { height: 35px; width: 44px; font-size: 21.875px; letter-spacing: -3.6041666666666665px;}"}},{"@context":"http://iiif.io/api/presentation/2/context.json","@id":"d99ed7ba-2eb4-4de9-9403-ed87168c686f","@type":"oa:Annotation","motivation":"sc:painting","annotatedBy":{"name":"OCR"},"resource":{"@type":"cnt:ContentAsText","format":"text/html","chars":"<span id='d99ed7ba-2eb4-4de9-9403-ed87168c686f' class='anno-d99ed7ba-2eb4-4de9-9403-ed87168c686f' data-letter-spacing='-0.15327380952380953'>Urbino</span>","language":"en"},"on":{"full":"https://readux.ecdsdev.org/iiif/v2/2qfw5j4k/canvas/2qfw5j4k_00000279.jpg","@type":"oa:SpecificResource","within":{"@id":"https://readux.ecdsdev.org/iiif/v2/2qfw5j4k/manifest","@type":"sc:Manifest"},"selector":{"@type":"oa:FragmentSelector","value":"xywh=5,792,42,43","item":{"@type":"oa:FragmentSelector"}}},"stylesheet":{"type":"CssStylesheet","value":".anno-d99ed7ba-2eb4-4de9-9403-ed87168c686f: { height: 43px; width: 42px; font-size: 26.875px; letter-spacing: -6.4375px;}"}},{"@context":"http://iiif.io/api/presentation/2/context.json","@id":"02715ff0-a12f-42c9-9dba-cdaaa38f5a60","@type":"oa:Annotation","motivation":"sc:painting","annotatedBy":{"name":"OCR"},"resource":{"@type":"cnt:ContentAsText","format":"text/html","chars":"<span id='02715ff0-a12f-42c9-9dba-cdaaa38f5a60' class='anno-02715ff0-a12f-42c9-9dba-cdaaa38f5a60' data-letter-spacing='-0.08658854166666667'>200</span>","language":"en"},"on":{"full":"https://readux.ecdsdev.org/iiif/v2/2qfw5j4k/canvas/2qfw5j4k_00000279.jpg","@type":"oa:SpecificResource","within":{"@id":"https://readux.ecdsdev.org/iiif/v2/2qfw5j4k/manifest","@type":"sc:Manifest"},"selector":{"@type":"oa:FragmentSelector","value":"xywh=-5,956,32,43","item":{"@type":"oa:FragmentSelector"}}},"stylesheet":{"type":"CssStylesheet","value":".anno-02715ff0-a12f-42c9-9dba-cdaaa38f5a60: { height: 43px; width: 32px; font-size: 26.875px; letter-spacing: -2.7708333333333335px;}"}},{"@context":"http://iiif.io/api/presentation/2/context.json","@id":"9de2f67b-24a4-41f3-8f8c-cfc7b5b59dc5","@type":"oa:Annotation","motivation":"sc:painting","annotatedBy":{"name":"OCR"},"resource":{"@type":"cnt:ContentAsText","format":"text/html","chars":"<span id='9de2f67b-24a4-41f3-8f8c-cfc7b5b59dc5' class='anno-9de2f67b-24a4-41f3-8f8c-cfc7b5b59dc5' data-letter-spacing='-0.028846153846153848'>M2</span>","language":"en"},"on":{"full":"https://readux.ecdsdev.org/iiif/v2/2qfw5j4k/canvas/2qfw5j4k_00000279.jpg","@type":"oa:SpecificResource","within":{"@id":"https://readux.ecdsdev.org/iiif/v2/2qfw5j4k/manifest","@type":"sc:Manifest"},"selector":{"@type":"oa:FragmentSelector","value":"xywh=30,954,26,44","item":{"@type":"oa:FragmentSelector"}}},"stylesheet":{"type":"CssStylesheet","value":".anno-9de2f67b-24a4-41f3-8f8c-cfc7b5b59dc5: { height: 44px; width: 26px; font-size: 27.5px; letter-spacing: -0.75px;}"}},{"@context":"http://iiif.io/api/presentation/2/context.json","@id":"0fcdecfc-da23-4c5c-8d4a-0b853414c61e","@type":"oa:Annotation","motivation":"sc:painting","annotatedBy":{"name":"OCR"},"resource":{"@type":"cnt:ContentAsText","format":"text/html","chars":"<span id='0fcdecfc-da23-4c5c-8d4a-0b853414c61e' class='anno-0fcdecfc-da23-4c5c-8d4a-0b853414c61e' data-letter-spacing='-0.1111111111111111'>pela</span>","language":"en"},"on":{"full":"https://readux.ecdsdev.org/iiif/v2/2qfw5j4k/canvas/2qfw5j4k_00000279.jpg","@type":"oa:SpecificResource","within":{"@id":"https://readux.ecdsdev.org/iiif/v2/2qfw5j4k/manifest","@type":"sc:Manifest"},"selector":{"@type":"oa:FragmentSelector","value":"xywh=-2,1012,45,52","item":{"@type":"oa:FragmentSelector"}}},"stylesheet":{"type":"CssStylesheet","value":".anno-0fcdecfc-da23-4c5c-8d4a-0b853414c61e: { height: 52px; width: 45px; font-size: 32.5px; letter-spacing: -5.0px;}"}},{"@context":"http://iiif.io/api/presentation/2/context.json","@id":"5f7242c2-b586-4576-82d0-30cbb8eca253","@type":"oa:Annotation","motivation":"sc:painting","annotatedBy":{"name":"OCR"},"resource":{"@type":"cnt:ContentAsText","format":"text/html","chars":"<span id='5f7242c2-b586-4576-82d0-30cbb8eca253' class='anno-5f7242c2-b586-4576-82d0-30cbb8eca253' data-letter-spacing='-0.90625'>se</span>","language":"en"},"on":{"full":"https://readux.ecdsdev.org/iiif/v2/2qfw5j4k/canvas/2qfw5j4k_00000279.jpg","@type":"oa:SpecificResource","within":{"@id":"https://readux.ecdsdev.org/iiif/v2/2qfw5j4k/manifest","@type":"sc:Manifest"},"selector":{"@type":"oa:FragmentSelector","value":"xywh=47,1010,12,54","item":{"@type":"oa:FragmentSelector"}}},"stylesheet":{"type":"CssStylesheet","value":".anno-5f7242c2-b586-4576-82d0-30cbb8eca253: { height: 54px; width: 12px; font-size: 33.75px; letter-spacing: -10.875px;}"}},{"@context":"http://iiif.io/api/presentation/2/context.json","@id":"adba431a-b1cf-4b40-9d95-215e0dd52240","@type":"oa:Annotation","motivation":"sc:painting","annotatedBy":{"name":"OCR"},"resource":{"@type":"cnt:ContentAsText","format":"text/html","chars":"<span id='adba431a-b1cf-4b40-9d95-215e0dd52240' class='anno-adba431a-b1cf-4b40-9d95-215e0dd52240' data-letter-spacing='-0.043821839080459765'>nam</span>","language":"en"},"on":{"full":"https://readux.ecdsdev.org/iiif/v2/2qfw5j4k/canvas/2qfw5j4k_00000279.jpg","@type":"oa:SpecificResource","within":{"@id":"https://readux.ecdsdev.org/iiif/v2/2qfw5j4k/manifest","@type":"sc:Manifest"},"selector":{"@type":"oa:FragmentSelector","value":"xywh=-3,1074,29,35","item":{"@type":"oa:FragmentSelector"}}},"stylesheet":{"type":"CssStylesheet","value":".anno-adba431a-b1cf-4b40-9d95-215e0dd52240: { height: 35px; width: 29px; font-size: 21.875px; letter-spacing: -1.2708333333333333px;}"}},{"@context":"http://iiif.io/api/presentation/2/context.json","@id":"428a9de2-2028-43da-94fc-04f1a7cf3050","@type":"oa:Annotation","motivation":"sc:painting","annotatedBy":{"name":"OCR"},"resource":{"@type":"cnt:ContentAsText","format":"text/html","chars":"<span id='428a9de2-2028-43da-94fc-04f1a7cf3050' class='anno-428a9de2-2028-43da-94fc-04f1a7cf3050' data-letter-spacing='-0.2152777777777778'>:</span>","language":"en"},"on":{"full":"https://readux.ecdsdev.org/iiif/v2/2qfw5j4k/canvas/2qfw5j4k_00000279.jpg","@type":"oa:SpecificResource","within":{"@id":"https://readux.ecdsdev.org/iiif/v2/2qfw5j4k/manifest","@type":"sc:Manifest"},"selector":{"@type":"oa:FragmentSelector","value":"xywh=30,1074,9,35","item":{"@type":"oa:FragmentSelector"}}},"stylesheet":{"type":"CssStylesheet","value":".anno-428a9de2-2028-43da-94fc-04f1a7cf3050: { height: 35px; width: 9px; font-size: 21.875px; letter-spacing: -1.9375px;}"}},{"@context":"http://iiif.io/api/presentation/2/context.json","@id":"66e8c54b-f8fd-453c-b931-1c1ce1a3f7e7","@type":"oa:Annotation","motivation":"sc:painting","annotatedBy":{"name":"OCR"},"resource":{"@type":"cnt:ContentAsText","format":"text/html","chars":"<span id='66e8c54b-f8fd-453c-b931-1c1ce1a3f7e7' class='anno-66e8c54b-f8fd-453c-b931-1c1ce1a3f7e7' data-letter-spacing='-0.05921052631578947'>CE</span>","language":"en"},"on":{"full":"https://readux.ecdsdev.org/iiif/v2/2qfw5j4k/canvas/2qfw5j4k_00000279.jpg","@type":"oa:SpecificResource","within":{"@id":"https://readux.ecdsdev.org/iiif/v2/2qfw5j4k/manifest","@type":"sc:Manifest"},"selector":{"@type":"oa:FragmentSelector","value":"xywh=39,1074,19,34","item":{"@type":"oa:FragmentSelector"}}},"stylesheet":{"type":"CssStylesheet","value":".anno-66e8c54b-f8fd-453c-b931-1c1ce1a3f7e7: { height: 34px; width: 19px; font-size: 21.25px; letter-spacing: -1.125px;}"}},{"@context":"http://iiif.io/api/presentation/2/context.json","@id":"ace39f5f-082e-4aed-b8f2-1ab827837256","@type":"oa:Annotation","motivation":"sc:painting","annotatedBy":{"name":"OCR"},"resource":{"@type":"cnt:ContentAsText","format":"text/html","chars":"<span id='ace39f5f-082e-4aed-b8f2-1ab827837256' class='anno-ace39f5f-082e-4aed-b8f2-1ab827837256' data-letter-spacing='0.43080357142857145'>I</span>","language":"en"},"on":{"full":"https://readux.ecdsdev.org/iiif/v2/2qfw5j4k/canvas/2qfw5j4k_00000279.jpg","@type":"oa:SpecificResource","within":{"@id":"https://readux.ecdsdev.org/iiif/v2/2qfw5j4k/manifest","@type":"sc:Manifest"},"selector":{"@type":"oa:FragmentSelector","value":"xywh=-12,1676,28,51","item":{"@type":"oa:FragmentSelector"}}},"stylesheet":{"type":"CssStylesheet","value":".anno-ace39f5f-082e-4aed-b8f2-1ab827837256: { height: 51px; width: 28px; font-size: 31.875px; letter-spacing: 12.0625px;}"}},{"@context":"http://iiif.io/api/presentation/2/context.json","@id":"f965eb3f-ee60-4ad5-a0fa-8422716f12c4","@type":"oa:Annotation","motivation":"sc:painting","annotatedBy":{"name":"OCR"},"resource":{"@type":"cnt:ContentAsText","format":"text/html","chars":"<span id='f965eb3f-ee60-4ad5-a0fa-8422716f12c4' class='anno-f965eb3f-ee60-4ad5-a0fa-8422716f12c4' data-letter-spacing='-0.11282467532467533'>allegro</span>","language":"en"},"on":{"full":"https://readux.ecdsdev.org/iiif/v2/2qfw5j4k/canvas/2qfw5j4k_00000279.jpg","@type":"oa:SpecificResource","within":{"@id":"https://readux.ecdsdev.org/iiif/v2/2qfw5j4k/manifest","@type":"sc:Manifest"},"selector":{"@type":"oa:FragmentSelector","value":"xywh=10,1671,55,45","item":{"@type":"oa:FragmentSelector"}}},"stylesheet":{"type":"CssStylesheet","value":".anno-f965eb3f-ee60-4ad5-a0fa-8422716f12c4: { height: 45px; width: 55px; font-size: 28.125px; letter-spacing: -6.205357142857143px;}"}},{"@context":"http://iiif.io/api/presentation/2/context.json","@id":"ab6e01d3-ccbf-4714-bb32-343adb22c17b","@type":"oa:Annotation","motivation":"sc:painting","annotatedBy":{"name":"OCR"},"resource":{"@type":"cnt:ContentAsText","format":"text/html","chars":"<span id='ab6e01d3-ccbf-4714-bb32-343adb22c17b' class='anno-ab6e01d3-ccbf-4714-bb32-343adb22c17b' data-letter-spacing='-0.09069767441860464'>retti</span>","language":"en"},"on":{"full":"https://readux.ecdsdev.org/iiif/v2/2qfw5j4k/canvas/2qfw5j4k_00000279.jpg","@type":"oa:SpecificResource","within":{"@id":"https://readux.ecdsdev.org/iiif/v2/2qfw5j4k/manifest","@type":"sc:Manifest"},"selector":{"@type":"oa:FragmentSelector","value":"xywh=-5,1724,43,40","item":{"@type":"oa:FragmentSelector"}}},"stylesheet":{"type":"CssStylesheet","value":".anno-ab6e01d3-ccbf-4714-bb32-343adb22c17b: { height: 40px; width: 43px; font-size: 25.0px; letter-spacing: -3.9px;}"}},{"@context":"http://iiif.io/api/presentation/2/context.json","@id":"f8b67056-3562-4af7-8539-76476d687e84","@type":"oa:Annotation","motivation":"sc:painting","annotatedBy":{"name":"OCR"},"resource":{"@type":"cnt:ContentAsText","format":"text/html","chars":"<span id='f8b67056-3562-4af7-8539-76476d687e84' class='anno-f8b67056-3562-4af7-8539-76476d687e84' data-letter-spacing='-0.30654761904761907'>com</span>","language":"en"},"on":{"full":"https://readux.ecdsdev.org/iiif/v2/2qfw5j4k/canvas/2qfw5j4k_00000279.jpg","@type":"oa:SpecificResource","within":{"@id":"https://readux.ecdsdev.org/iiif/v2/2qfw5j4k/manifest","@type":"sc:Manifest"},"selector":{"@type":"oa:FragmentSelector","value":"xywh=38,1720,21,43","item":{"@type":"oa:FragmentSelector"}}},"stylesheet":{"type":"CssStylesheet","value":".anno-f8b67056-3562-4af7-8539-76476d687e84: { height: 43px; width: 21px; font-size: 26.875px; letter-spacing: -6.4375px;}"}},{"@context":"http://iiif.io/api/presentation/2/context.json","@id":"86338a0e-d5e3-4414-8c11-db6c4161d42a","@type":"oa:Annotation","motivation":"sc:painting","annotatedBy":{"name":"OCR"},"resource":{"@type":"cnt:ContentAsText","format":"text/html","chars":"<span id='86338a0e-d5e3-4414-8c11-db6c4161d42a' class='anno-86338a0e-d5e3-4414-8c11-db6c4161d42a' data-letter-spacing='0.019230769230769232'>il</span>","language":"en"},"on":{"full":"https://readux.ecdsdev.org/iiif/v2/2qfw5j4k/canvas/2qfw5j4k_00000279.jpg","@type":"oa:SpecificResource","within":{"@id":"https://readux.ecdsdev.org/iiif/v2/2qfw5j4k/manifest","@type":"sc:Manifest"},"selector":{"@type":"oa:FragmentSelector","value":"xywh=5,1778,26,40","item":{"@type":"oa:FragmentSelector"}}},"stylesheet":{"type":"CssStylesheet","value":".anno-86338a0e-d5e3-4414-8c11-db6c4161d42a: { height: 40px; width: 26px; font-size: 25.0px; letter-spacing: 0.5px;}"}},{"@context":"http://iiif.io/api/presentation/2/context.json","@id":"6efe4e83-42c8-4a05-8073-5aa589febd86","@type":"oa:Annotation","motivation":"sc:painting","annotatedBy":{"name":"OCR"},"resource":{"@type":"cnt:ContentAsText","format":"text/html","chars":"<span id='6efe4e83-42c8-4a05-8073-5aa589febd86' class='anno-6efe4e83-42c8-4a05-8073-5aa589febd86' data-letter-spacing='-0.09821428571428571'>colo</span>","language":"en"},"on":{"full":"https://readux.ecdsdev.org/iiif/v2/2qfw5j4k/canvas/2qfw5j4k_00000279.jpg","@type":"oa:SpecificResource","within":{"@id":"https://readux.ecdsdev.org/iiif/v2/2qfw5j4k/manifest","@type":"sc:Manifest"},"selector":{"@type":"oa:FragmentSelector","value":"xywh=29,1773,35,39","item":{"@type":"oa:FragmentSelector"}}},"stylesheet":{"type":"CssStylesheet","value":".anno-6efe4e83-42c8-4a05-8073-5aa589febd86: { height: 39px; width: 35px; font-size: 24.375px; letter-spacing: -3.4375px;}"}},{"@context":"http://iiif.io/api/presentation/2/context.json","@id":"682f529d-0d7a-48bb-a6b4-adf589c65da7","@type":"oa:Annotation","motivation":"sc:painting","annotatedBy":{"name":"OCR"},"resource":{"@type":"cnt:ContentAsText","format":"text/html","chars":"<span id='682f529d-0d7a-48bb-a6b4-adf589c65da7' class='anno-682f529d-0d7a-48bb-a6b4-adf589c65da7' data-letter-spacing='0.0024509803921568627'>ato</span>","language":"en"},"on":{"full":"https://readux.ecdsdev.org/iiif/v2/2qfw5j4k/canvas/2qfw5j4k_00000279.jpg","@type":"oa:SpecificResource","within":{"@id":"https://readux.ecdsdev.org/iiif/v2/2qfw5j4k/manifest","@type":"sc:Manifest"},"selector":{"@type":"oa:FragmentSelector","value":"xywh=0,1999,34,36","item":{"@type":"oa:FragmentSelector"}}},"stylesheet":{"type":"CssStylesheet","value":".anno-682f529d-0d7a-48bb-a6b4-adf589c65da7: { height: 36px; width: 34px; font-size: 22.5px; letter-spacing: 0.08333333333333333px;}"}},{"@context":"http://iiif.io/api/presentation/2/context.json","@id":"d69a1639-e135-4eb4-80fe-b89e7ef1aaa6","@type":"oa:Annotation","motivation":"sc:painting","annotatedBy":{"name":"OCR"},"resource":{"@type":"cnt:ContentAsText","format":"text/html","chars":"<span id='d69a1639-e135-4eb4-80fe-b89e7ef1aaa6' class='anno-d69a1639-e135-4eb4-80fe-b89e7ef1aaa6' data-letter-spacing='0.08051470588235293'>2.COM</span>","language":"en"},"on":{"full":"https://readux.ecdsdev.org/iiif/v2/2qfw5j4k/canvas/2qfw5j4k_00000279.jpg","@type":"oa:SpecificResource","within":{"@id":"https://readux.ecdsdev.org/iiif/v2/2qfw5j4k/manifest","@type":"sc:Manifest"},"selector":{"@type":"oa:FragmentSelector","value":"xywh=-10,2060,68,26","item":{"@type":"oa:FragmentSelector"}}},"stylesheet":{"type":"CssStylesheet","value":".anno-d69a1639-e135-4eb4-80fe-b89e7ef1aaa6: { height: 26px; width: 68px; font-size: 16.25px; letter-spacing: 5.475px;}"}},{"@context":"http://iiif.io/api/presentation/2/context.json","@id":"0675ee49-d754-4e61-be00-ce8fec63daa3","@type":"oa:Annotation","motivation":"sc:painting","annotatedBy":{"name":"OCR"},"resource":{"@type":"cnt:ContentAsText","format":"text/html","chars":"<span id='0675ee49-d754-4e61-be00-ce8fec63daa3' class='anno-0675ee49-d754-4e61-be00-ce8fec63daa3' data-letter-spacing='0.010638297872340425'>nato</span>","language":"en"},"on":{"full":"https://readux.ecdsdev.org/iiif/v2/2qfw5j4k/canvas/2qfw5j4k_00000279.jpg","@type":"oa:SpecificResource","within":{"@id":"https://readux.ecdsdev.org/iiif/v2/2qfw5j4k/manifest","@type":"sc:Manifest"},"selector":{"@type":"oa:FragmentSelector","value":"xywh=-7,2103,47,36","item":{"@type":"oa:FragmentSelector"}}},"stylesheet":{"type":"CssStylesheet","value":".anno-0675ee49-d754-4e61-be00-ce8fec63daa3: { height: 36px; width: 47px; font-size: 22.5px; letter-spacing: 0.5px;}"}},{"@context":"http://iiif.io/api/presentation/2/context.json","@id":"22afa70c-a973-4841-b18d-cc2dc5c4585d","@type":"oa:Annotation","motivation":"sc:painting","annotatedBy":{"name":"OCR"},"resource":{"@type":"cnt:ContentAsText","format":"text/html","chars":"<span id='22afa70c-a973-4841-b18d-cc2dc5c4585d' class='anno-22afa70c-a973-4841-b18d-cc2dc5c4585d' data-letter-spacing='-0.21691176470588236'>di</span>","language":"en"},"on":{"full":"https://readux.ecdsdev.org/iiif/v2/2qfw5j4k/canvas/2qfw5j4k_00000279.jpg","@type":"oa:SpecificResource","within":{"@id":"https://readux.ecdsdev.org/iiif/v2/2qfw5j4k/manifest","@type":"sc:Manifest"},"selector":{"@type":"oa:FragmentSelector","value":"xywh=41,2097,17,39","item":{"@type":"oa:FragmentSelector"}}},"stylesheet":{"type":"CssStylesheet","value":".anno-22afa70c-a973-4841-b18d-cc2dc5c4585d: { height: 39px; width: 17px; font-size: 24.375px; letter-spacing: -3.6875px;}"}},{"@context":"http://iiif.io/api/presentation/2/context.json","@id":"9ae95777-691b-46eb-82cb-1e98e2bfb1a8","@type":"oa:Annotation","motivation":"sc:painting","annotatedBy":{"name":"OCR"},"resource":{"@type":"cnt:ContentAsText","format":"text/html","chars":"<span id='9ae95777-691b-46eb-82cb-1e98e2bfb1a8' class='anno-9ae95777-691b-46eb-82cb-1e98e2bfb1a8' data-letter-spacing='0.06979166666666667'>otara</span>","language":"en"},"on":{"full":"https://readux.ecdsdev.org/iiif/v2/2qfw5j4k/canvas/2qfw5j4k_00000279.jpg","@type":"oa:SpecificResource","within":{"@id":"https://readux.ecdsdev.org/iiif/v2/2qfw5j4k/manifest","@type":"sc:Manifest"},"selector":{"@type":"oa:FragmentSelector","value":"xywh=-3,2215,60,25","item":{"@type":"oa:FragmentSelector"}}},"stylesheet":{"type":"CssStylesheet","value":".anno-9ae95777-691b-46eb-82cb-1e98e2bfb1a8: { height: 25px; width: 60px; font-size: 15.625px; letter-spacing: 4.1875px;}"}},{"@context":"http://iiif.io/api/presentation/2/context.json","@id":"ce57f631-f383-4e84-9db3-ce50d691a2e1","@type":"oa:Annotation","motivation":"sc:painting","annotatedBy":{"name":"OCR"},"resource":{"@type":"cnt:ContentAsText","format":"text/html","chars":"<span id='ce57f631-f383-4e84-9db3-ce50d691a2e1' class='anno-ce57f631-f383-4e84-9db3-ce50d691a2e1' data-letter-spacing='-0.037162162162162164'>Sran</span>","language":"en"},"on":{"full":"https://readux.ecdsdev.org/iiif/v2/2qfw5j4k/canvas/2qfw5j4k_00000279.jpg","@type":"oa:SpecificResource","within":{"@id":"https://readux.ecdsdev.org/iiif/v2/2qfw5j4k/manifest","@type":"sc:Manifest"},"selector":{"@type":"oa:FragmentSelector","value":"xywh=2,418,37,34","item":{"@type":"oa:FragmentSelector"}}},"stylesheet":{"type":"CssStylesheet","value":".anno-ce57f631-f383-4e84-9db3-ce50d691a2e1: { height: 34px; width: 37px; font-size: 21.25px; letter-spacing: -1.375px;}"}},{"@context":"http://iiif.io/api/presentation/2/context.json","@id":"400252b8-66e6-40dd-a88b-e25c79c4f40a","@type":"oa:Annotation","motivation":"sc:painting","annotatedBy":{"name":"OCR"},"resource":{"@type":"cnt:ContentAsText","format":"text/html","chars":"<span id='400252b8-66e6-40dd-a88b-e25c79c4f40a' class='anno-400252b8-66e6-40dd-a88b-e25c79c4f40a' data-letter-spacing='-0.08191287878787878'>terali</span>","language":"en"},"on":{"full":"https://readux.ecdsdev.org/iiif/v2/2qfw5j4k/canvas/2qfw5j4k_00000279.jpg","@type":"oa:SpecificResource","within":{"@id":"https://readux.ecdsdev.org/iiif/v2/2qfw5j4k/manifest","@type":"sc:Manifest"},"selector":{"@type":"oa:FragmentSelector","value":"xywh=2,474,44,35","item":{"@type":"oa:FragmentSelector"}}},"stylesheet":{"type":"CssStylesheet","value":".anno-400252b8-66e6-40dd-a88b-e25c79c4f40a: { height: 35px; width: 44px; font-size: 21.875px; letter-spacing: -3.6041666666666665px;}"}},{"@context":"http://iiif.io/api/presentation/2/context.json","@id":"d99ed7ba-2eb4-4de9-9403-ed87168c686f","@type":"oa:Annotation","motivation":"sc:painting","annotatedBy":{"name":"OCR"},"resource":{"@type":"cnt:ContentAsText","format":"text/html","chars":"<span id='d99ed7ba-2eb4-4de9-9403-ed87168c686f' class='anno-d99ed7ba-2eb4-4de9-9403-ed87168c686f' data-letter-spacing='-0.15327380952380953'>Urbino</span>","language":"en"},"on":{"full":"https://readux.ecdsdev.org/iiif/v2/2qfw5j4k/canvas/2qfw5j4k_00000279.jpg","@type":"oa:SpecificResource","within":{"@id":"https://readux.ecdsdev.org/iiif/v2/2qfw5j4k/manifest","@type":"sc:Manifest"},"selector":{"@type":"oa:FragmentSelector","value":"xywh=5,792,42,43","item":{"@type":"oa:FragmentSelector"}}},"stylesheet":{"type":"CssStylesheet","value":".anno-d99ed7ba-2eb4-4de9-9403-ed87168c686f: { height: 43px; width: 42px; font-size: 26.875px; letter-spacing: -6.4375px;}"}},{"@context":"http://iiif.io/api/presentation/2/context.json","@id":"02715ff0-a12f-42c9-9dba-cdaaa38f5a60","@type":"oa:Annotation","motivation":"sc:painting","annotatedBy":{"name":"OCR"},"resource":{"@type":"cnt:ContentAsText","format":"text/html","chars":"<span id='02715ff0-a12f-42c9-9dba-cdaaa38f5a60' class='anno-02715ff0-a12f-42c9-9dba-cdaaa38f5a60' data-letter-spacing='-0.08658854166666667'>200</span>","language":"en"},"on":{"full":"https://readux.ecdsdev.org/iiif/v2/2qfw5j4k/canvas/2qfw5j4k_00000279.jpg","@type":"oa:SpecificResource","within":{"@id":"https://readux.ecdsdev.org/iiif/v2/2qfw5j4k/manifest","@type":"sc:Manifest"},"selector":{"@type":"oa:FragmentSelector","value":"xywh=-5,956,32,43","item":{"@type":"oa:FragmentSelector"}}},"stylesheet":{"type":"CssStylesheet","value":".anno-02715ff0-a12f-42c9-9dba-cdaaa38f5a60: { height: 43px; width: 32px; font-size: 26.875px; letter-spacing: -2.7708333333333335px;}"}},{"@context":"http://iiif.io/api/presentation/2/context.json","@id":"9de2f67b-24a4-41f3-8f8c-cfc7b5b59dc5","@type":"oa:Annotation","motivation":"sc:painting","annotatedBy":{"name":"OCR"},"resource":{"@type":"cnt:ContentAsText","format":"text/html","chars":"<span id='9de2f67b-24a4-41f3-8f8c-cfc7b5b59dc5' class='anno-9de2f67b-24a4-41f3-8f8c-cfc7b5b59dc5' data-letter-spacing='-0.028846153846153848'>M2</span>","language":"en"},"on":{"full":"https://readux.ecdsdev.org/iiif/v2/2qfw5j4k/canvas/2qfw5j4k_00000279.jpg","@type":"oa:SpecificResource","within":{"@id":"https://readux.ecdsdev.org/iiif/v2/2qfw5j4k/manifest","@type":"sc:Manifest"},"selector":{"@type":"oa:FragmentSelector","value":"xywh=30,954,26,44","item":{"@type":"oa:FragmentSelector"}}},"stylesheet":{"type":"CssStylesheet","value":".anno-9de2f67b-24a4-41f3-8f8c-cfc7b5b59dc5: { height: 44px; width: 26px; font-size: 27.5px; letter-spacing: -0.75px;}"}},{"@context":"http://iiif.io/api/presentation/2/context.json","@id":"0fcdecfc-da23-4c5c-8d4a-0b853414c61e","@type":"oa:Annotation","motivation":"sc:painting","annotatedBy":{"name":"OCR"},"resource":{"@type":"cnt:ContentAsText","format":"text/html","chars":"<span id='0fcdecfc-da23-4c5c-8d4a-0b853414c61e' class='anno-0fcdecfc-da23-4c5c-8d4a-0b853414c61e' data-letter-spacing='-0.1111111111111111'>pela</span>","language":"en"},"on":{"full":"https://readux.ecdsdev.org/iiif/v2/2qfw5j4k/canvas/2qfw5j4k_00000279.jpg","@type":"oa:SpecificResource","within":{"@id":"https://readux.ecdsdev.org/iiif/v2/2qfw5j4k/manifest","@type":"sc:Manifest"},"selector":{"@type":"oa:FragmentSelector","value":"xywh=-2,1012,45,52","item":{"@type":"oa:FragmentSelector"}}},"stylesheet":{"type":"CssStylesheet","value":".anno-0fcdecfc-da23-4c5c-8d4a-0b853414c61e: { height: 52px; width: 45px; font-size: 32.5px; letter-spacing: -5.0px;}"}},{"@context":"http://iiif.io/api/presentation/2/context.json","@id":"5f7242c2-b586-4576-82d0-30cbb8eca253","@type":"oa:Annotation","motivation":"sc:painting","annotatedBy":{"name":"OCR"},"resource":{"@type":"cnt:ContentAsText","format":"text/html","chars":"<span id='5f7242c2-b586-4576-82d0-30cbb8eca253' class='anno-5f7242c2-b586-4576-82d0-30cbb8eca253' data-letter-spacing='-0.90625'>se</span>","language":"en"},"on":{"full":"https://readux.ecdsdev.org/iiif/v2/2qfw5j4k/canvas/2qfw5j4k_00000279.jpg","@type":"oa:SpecificResource","within":{"@id":"https://readux.ecdsdev.org/iiif/v2/2qfw5j4k/manifest","@type":"sc:Manifest"},"selector":{"@type":"oa:FragmentSelector","value":"xywh=47,1010,12,54","item":{"@type":"oa:FragmentSelector"}}},"stylesheet":{"type":"CssStylesheet","value":".anno-5f7242c2-b586-4576-82d0-30cbb8eca253: { height: 54px; width: 12px; font-size: 33.75px; letter-spacing: -10.875px;}"}},{"@context":"http://iiif.io/api/presentation/2/context.json","@id":"adba431a-b1cf-4b40-9d95-215e0dd52240","@type":"oa:Annotation","motivation":"sc:painting","annotatedBy":{"name":"OCR"},"resource":{"@type":"cnt:ContentAsText","format":"text/html","chars":"<span id='adba431a-b1cf-4b40-9d95-215e0dd52240' class='anno-adba431a-b1cf-4b40-9d95-215e0dd52240' data-letter-spacing='-0.043821839080459765'>nam</span>","language":"en"},"on":{"full":"https://readux.ecdsdev.org/iiif/v2/2qfw5j4k/canvas/2qfw5j4k_00000279.jpg","@type":"oa:SpecificResource","within":{"@id":"https://readux.ecdsdev.org/iiif/v2/2qfw5j4k/manifest","@type":"sc:Manifest"},"selector":{"@type":"oa:FragmentSelector","value":"xywh=-3,1074,29,35","item":{"@type":"oa:FragmentSelector"}}},"stylesheet":{"type":"CssStylesheet","value":".anno-adba431a-b1cf-4b40-9d95-215e0dd52240: { height: 35px; width: 29px; font-size: 21.875px; letter-spacing: -1.2708333333333333px;}"}},{"@context":"http://iiif.io/api/presentation/2/context.json","@id":"428a9de2-2028-43da-94fc-04f1a7cf3050","@type":"oa:Annotation","motivation":"sc:painting","annotatedBy":{"name":"OCR"},"resource":{"@type":"cnt:ContentAsText","format":"text/html","chars":"<span id='428a9de2-2028-43da-94fc-04f1a7cf3050' class='anno-428a9de2-2028-43da-94fc-04f1a7cf3050' data-letter-spacing='-0.2152777777777778'>:</span>","language":"en"},"on":{"full":"https://readux.ecdsdev.org/iiif/v2/2qfw5j4k/canvas/2qfw5j4k_00000279.jpg","@type":"oa:SpecificResource","within":{"@id":"https://readux.ecdsdev.org/iiif/v2/2qfw5j4k/manifest","@type":"sc:Manifest"},"selector":{"@type":"oa:FragmentSelector","value":"xywh=30,1074,9,35","item":{"@type":"oa:FragmentSelector"}}},"stylesheet":{"type":"CssStylesheet","value":".anno-428a9de2-2028-43da-94fc-04f1a7cf3050: { height: 35px; width: 9px; font-size: 21.875px; letter-spacing: -1.9375px;}"}},{"@context":"http://iiif.io/api/presentation/2/context.json","@id":"66e8c54b-f8fd-453c-b931-1c1ce1a3f7e7","@type":"oa:Annotation","motivation":"sc:painting","annotatedBy":{"name":"OCR"},"resource":{"@type":"cnt:ContentAsText","format":"text/html","chars":"<span id='66e8c54b-f8fd-453c-b931-1c1ce1a3f7e7' class='anno-66e8c54b-f8fd-453c-b931-1c1ce1a3f7e7' data-letter-spacing='-0.05921052631578947'>CE</span>","language":"en"},"on":{"full":"https://readux.ecdsdev.org/iiif/v2/2qfw5j4k/canvas/2qfw5j4k_00000279.jpg","@type":"oa:SpecificResource","within":{"@id":"https://readux.ecdsdev.org/iiif/v2/2qfw5j4k/manifest","@type":"sc:Manifest"},"selector":{"@type":"oa:FragmentSelector","value":"xywh=39,1074,19,34","item":{"@type":"oa:FragmentSelector"}}},"stylesheet":{"type":"CssStylesheet","value":".anno-66e8c54b-f8fd-453c-b931-1c1ce1a3f7e7: { height: 34px; width: 19px; font-size: 21.25px; letter-spacing: -1.125px;}"}},{"@context":"http://iiif.io/api/presentation/2/context.json","@id":"ace39f5f-082e-4aed-b8f2-1ab827837256","@type":"oa:Annotation","motivation":"sc:painting","annotatedBy":{"name":"OCR"},"resource":{"@type":"cnt:ContentAsText","format":"text/html","chars":"<span id='ace39f5f-082e-4aed-b8f2-1ab827837256' class='anno-ace39f5f-082e-4aed-b8f2-1ab827837256' data-letter-spacing='0.43080357142857145'>I</span>","language":"en"},"on":{"full":"https://readux.ecdsdev.org/iiif/v2/2qfw5j4k/canvas/2qfw5j4k_00000279.jpg","@type":"oa:SpecificResource","within":{"@id":"https://readux.ecdsdev.org/iiif/v2/2qfw5j4k/manifest","@type":"sc:Manifest"},"selector":{"@type":"oa:FragmentSelector","value":"xywh=-12,1676,28,51","item":{"@type":"oa:FragmentSelector"}}},"stylesheet":{"type":"CssStylesheet","value":".anno-ace39f5f-082e-4aed-b8f2-1ab827837256: { height: 51px; width: 28px; font-size: 31.875px; letter-spacing: 12.0625px;}"}},{"@context":"http://iiif.io/api/presentation/2/context.json","@id":"f965eb3f-ee60-4ad5-a0fa-8422716f12c4","@type":"oa:Annotation","motivation":"sc:painting","annotatedBy":{"name":"OCR"},"resource":{"@type":"cnt:ContentAsText","format":"text/html","chars":"<span id='f965eb3f-ee60-4ad5-a0fa-8422716f12c4' class='anno-f965eb3f-ee60-4ad5-a0fa-8422716f12c4' data-letter-spacing='-0.11282467532467533'>allegro</span>","language":"en"},"on":{"full":"https://readux.ecdsdev.org/iiif/v2/2qfw5j4k/canvas/2qfw5j4k_00000279.jpg","@type":"oa:SpecificResource","within":{"@id":"https://readux.ecdsdev.org/iiif/v2/2qfw5j4k/manifest","@type":"sc:Manifest"},"selector":{"@type":"oa:FragmentSelector","value":"xywh=10,1671,55,45","item":{"@type":"oa:FragmentSelector"}}},"stylesheet":{"type":"CssStylesheet","value":".anno-f965eb3f-ee60-4ad5-a0fa-8422716f12c4: { height: 45px; width: 55px; font-size: 28.125px; letter-spacing: -6.205357142857143px;}"}},{"@context":"http://iiif.io/api/presentation/2/context.json","@id":"ab6e01d3-ccbf-4714-bb32-343adb22c17b","@type":"oa:Annotation","motivation":"sc:painting","annotatedBy":{"name":"OCR"},"resource":{"@type":"cnt:ContentAsText","format":"text/html","chars":"<span id='ab6e01d3-ccbf-4714-bb32-343adb22c17b' class='anno-ab6e01d3-ccbf-4714-bb32-343adb22c17b' data-letter-spacing='-0.09069767441860464'>retti</span>","language":"en"},"on":{"full":"https://readux.ecdsdev.org/iiif/v2/2qfw5j4k/canvas/2qfw5j4k_00000279.jpg","@type":"oa:SpecificResource","within":{"@id":"https://readux.ecdsdev.org/iiif/v2/2qfw5j4k/manifest","@type":"sc:Manifest"},"selector":{"@type":"oa:FragmentSelector","value":"xywh=-5,1724,43,40","item":{"@type":"oa:FragmentSelector"}}},"stylesheet":{"type":"CssStylesheet","value":".anno-ab6e01d3-ccbf-4714-bb32-343adb22c17b: { height: 40px; width: 43px; font-size: 25.0px; letter-spacing: -3.9px;}"}},{"@context":"http://iiif.io/api/presentation/2/context.json","@id":"f8b67056-3562-4af7-8539-76476d687e84","@type":"oa:Annotation","motivation":"sc:painting","annotatedBy":{"name":"OCR"},"resource":{"@type":"cnt:ContentAsText","format":"text/html","chars":"<span id='f8b67056-3562-4af7-8539-76476d687e84' class='anno-f8b67056-3562-4af7-8539-76476d687e84' data-letter-spacing='-0.30654761904761907'>com</span>","language":"en"},"on":{"full":"https://readux.ecdsdev.org/iiif/v2/2qfw5j4k/canvas/2qfw5j4k_00000279.jpg","@type":"oa:SpecificResource","within":{"@id":"https://readux.ecdsdev.org/iiif/v2/2qfw5j4k/manifest","@type":"sc:Manifest"},"selector":{"@type":"oa:FragmentSelector","value":"xywh=38,1720,21,43","item":{"@type":"oa:FragmentSelector"}}},"stylesheet":{"type":"CssStylesheet","value":".anno-f8b67056-3562-4af7-8539-76476d687e84: { height: 43px; width: 21px; font-size: 26.875px; letter-spacing: -6.4375px;}"}},{"@context":"http://iiif.io/api/presentation/2/context.json","@id":"86338a0e-d5e3-4414-8c11-db6c4161d42a","@type":"oa:Annotation","motivation":"sc:painting","annotatedBy":{"name":"OCR"},"resource":{"@type":"cnt:ContentAsText","format":"text/html","chars":"<span id='86338a0e-d5e3-4414-8c11-db6c4161d42a' class='anno-86338a0e-d5e3-4414-8c11-db6c4161d42a' data-letter-spacing='0.019230769230769232'>il</span>","language":"en"},"on":{"full":"https://readux.ecdsdev.org/iiif/v2/2qfw5j4k/canvas/2qfw5j4k_00000279.jpg","@type":"oa:SpecificResource","within":{"@id":"https://readux.ecdsdev.org/iiif/v2/2qfw5j4k/manifest","@type":"sc:Manifest"},"selector":{"@type":"oa:FragmentSelector","value":"xywh=5,1778,26,40","item":{"@type":"oa:FragmentSelector"}}},"stylesheet":{"type":"CssStylesheet","value":".anno-86338a0e-d5e3-4414-8c11-db6c4161d42a: { height: 40px; width: 26px; font-size: 25.0px; letter-spacing: 0.5px;}"}},{"@context":"http://iiif.io/api/presentation/2/context.json","@id":"6efe4e83-42c8-4a05-8073-5aa589febd86","@type":"oa:Annotation","motivation":"sc:painting","annotatedBy":{"name":"OCR"},"resource":{"@type":"cnt:ContentAsText","format":"text/html","chars":"<span id='6efe4e83-42c8-4a05-8073-5aa589febd86' class='anno-6efe4e83-42c8-4a05-8073-5aa589febd86' data-letter-spacing='-0.09821428571428571'>colo</span>","language":"en"},"on":{"full":"https://readux.ecdsdev.org/iiif/v2/2qfw5j4k/canvas/2qfw5j4k_00000279.jpg","@type":"oa:SpecificResource","within":{"@id":"https://readux.ecdsdev.org/iiif/v2/2qfw5j4k/manifest","@type":"sc:Manifest"},"selector":{"@type":"oa:FragmentSelector","value":"xywh=29,1773,35,39","item":{"@type":"oa:FragmentSelector"}}},"stylesheet":{"type":"CssStylesheet","value":".anno-6efe4e83-42c8-4a05-8073-5aa589febd86: { height: 39px; width: 35px; font-size: 24.375px; letter-spacing: -3.4375px;}"}},{"@context":"http://iiif.io/api/presentation/2/context.json","@id":"682f529d-0d7a-48bb-a6b4-adf589c65da7","@type":"oa:Annotation","motivation":"sc:painting","annotatedBy":{"name":"OCR"},"resource":{"@type":"cnt:ContentAsText","format":"text/html","chars":"<span id='682f529d-0d7a-48bb-a6b4-adf589c65da7' class='anno-682f529d-0d7a-48bb-a6b4-adf589c65da7' data-letter-spacing='0.0024509803921568627'>ato</span>","language":"en"},"on":{"full":"https://readux.ecdsdev.org/iiif/v2/2qfw5j4k/canvas/2qfw5j4k_00000279.jpg","@type":"oa:SpecificResource","within":{"@id":"https://readux.ecdsdev.org/iiif/v2/2qfw5j4k/manifest","@type":"sc:Manifest"},"selector":{"@type":"oa:FragmentSelector","value":"xywh=0,1999,34,36","item":{"@type":"oa:FragmentSelector"}}},"stylesheet":{"type":"CssStylesheet","value":".anno-682f529d-0d7a-48bb-a6b4-adf589c65da7: { height: 36px; width: 34px; font-size: 22.5px; letter-spacing: 0.08333333333333333px;}"}},{"@context":"http://iiif.io/api/presentation/2/context.json","@id":"d69a1639-e135-4eb4-80fe-b89e7ef1aaa6","@type":"oa:Annotation","motivation":"sc:painting","annotatedBy":{"name":"OCR"},"resource":{"@type":"cnt:ContentAsText","format":"text/html","chars":"<span id='d69a1639-e135-4eb4-80fe-b89e7ef1aaa6' class='anno-d69a1639-e135-4eb4-80fe-b89e7ef1aaa6' data-letter-spacing='0.08051470588235293'>2.COM</span>","language":"en"},"on":{"full":"https://readux.ecdsdev.org/iiif/v2/2qfw5j4k/canvas/2qfw5j4k_00000279.jpg","@type":"oa:SpecificResource","within":{"@id":"https://readux.ecdsdev.org/iiif/v2/2qfw5j4k/manifest","@type":"sc:Manifest"},"selector":{"@type":"oa:FragmentSelector","value":"xywh=-10,2060,68,26","item":{"@type":"oa:FragmentSelector"}}},"stylesheet":{"type":"CssStylesheet","value":".anno-d69a1639-e135-4eb4-80fe-b89e7ef1aaa6: { height: 26px; width: 68px; font-size: 16.25px; letter-spacing: 5.475px;}"}},{"@context":"http://iiif.io/api/presentation/2/context.json","@id":"0675ee49-d754-4e61-be00-ce8fec63daa3","@type":"oa:Annotation","motivation":"sc:painting","annotatedBy":{"name":"OCR"},"resource":{"@type":"cnt:ContentAsText","format":"text/html","chars":"<span id='0675ee49-d754-4e61-be00-ce8fec63daa3' class='anno-0675ee49-d754-4e61-be00-ce8fec63daa3' data-letter-spacing='0.010638297872340425'>nato</span>","language":"en"},"on":{"full":"https://readux.ecdsdev.org/iiif/v2/2qfw5j4k/canvas/2qfw5j4k_00000279.jpg","@type":"oa:SpecificResource","within":{"@id":"https://readux.ecdsdev.org/iiif/v2/2qfw5j4k/manifest","@type":"sc:Manifest"},"selector":{"@type":"oa:FragmentSelector","value":"xywh=-7,2103,47,36","item":{"@type":"oa:FragmentSelector"}}},"stylesheet":{"type":"CssStylesheet","value":".anno-0675ee49-d754-4e61-be00-ce8fec63daa3: { height: 36px; width: 47px; font-size: 22.5px; letter-spacing: 0.5px;}"}},{"@context":"http://iiif.io/api/presentation/2/context.json","@id":"22afa70c-a973-4841-b18d-cc2dc5c4585d","@type":"oa:Annotation","motivation":"sc:painting","annotatedBy":{"name":"OCR"},"resource":{"@type":"cnt:ContentAsText","format":"text/html","chars":"<span id='22afa70c-a973-4841-b18d-cc2dc5c4585d' class='anno-22afa70c-a973-4841-b18d-cc2dc5c4585d' data-letter-spacing='-0.21691176470588236'>di</span>","language":"en"},"on":{"full":"https://readux.ecdsdev.org/iiif/v2/2qfw5j4k/canvas/2qfw5j4k_00000279.jpg","@type":"oa:SpecificResource","within":{"@id":"https://readux.ecdsdev.org/iiif/v2/2qfw5j4k/manifest","@type":"sc:Manifest"},"selector":{"@type":"oa:FragmentSelector","value":"xywh=41,2097,17,39","item":{"@type":"oa:FragmentSelector"}}},"stylesheet":{"type":"CssStylesheet","value":".anno-22afa70c-a973-4841-b18d-cc2dc5c4585d: { height: 39px; width: 17px; font-size: 24.375px; letter-spacing: -3.6875px;}"}},{"@context":"http://iiif.io/api/presentation/2/context.json","@id":"9ae95777-691b-46eb-82cb-1e98e2bfb1a8","@type":"oa:Annotation","motivation":"sc:painting","annotatedBy":{"name":"OCR"},"resource":{"@type":"cnt:ContentAsText","format":"text/html","chars":"<span id='9ae95777-691b-46eb-82cb-1e98e2bfb1a8' class='anno-9ae95777-691b-46eb-82cb-1e98e2bfb1a8' data-letter-spacing='0.06979166666666667'>otara</span>","language":"en"},"on":{"full":"https://readux.ecdsdev.org/iiif/v2/2qfw5j4k/canvas/2qfw5j4k_00000279.jpg","@type":"oa:SpecificResource","within":{"@id":"https://readux.ecdsdev.org/iiif/v2/2qfw5j4k/manifest","@type":"sc:Manifest"},"selector":{"@type":"oa:FragmentSelector","value":"xywh=-3,2215,60,25","item":{"@type":"oa:FragmentSelector"}}},"stylesheet":{"type":"CssStylesheet","value":".anno-9ae95777-691b-46eb-82cb-1e98e2bfb1a8: { height: 25px; width: 60px; font-size: 15.625px; letter-spacing: 4.1875px;}"}}]}